uhi/__init__.py
uhi/_version.py
uhi/_version.pyi
uhi/numpy_plottable.py
uhi/py.typed
uhi/typing/__init__.py
uhi/typing/plottable.py
uhi-0.3.3.dist-info/METADATA
uhi-0.3.3.dist-info/WHEEL
uhi-0.3.3.dist-info/licenses/LICENSE
uhi-0.3.3.dist-info/RECORD
