Metadata-Version: 2.1
Name: uhi
Version: 0.3.3
Summary: Unified Histogram Interface: tools to help library authors work with histograms
Project-URL: Homepage, https://github.com/Scikit-HEP/uhi
Project-URL: Repository, https://github.com/Scikit-HEP/uhi
Project-URL: Documentation, https://uhi.readthedocs.io/en/latest/
Project-URL: Changelog, https://github.com/scikit-hep/uhi/releases
Author-email: Henry Schreiner <henryschreineriii@gmail.com>, Hans Dembinski <hans.dembinski@gmail.com>, Jim Pivaski <pivarski@princeton.edu>
Maintainer-email: The Scikit-HEP admins <scikit-hep-admins@googlegroups.com>
License: BSD 3-Clause License
License-File: LICENSE
Classifier: Development Status :: 4 - Beta
Classifier: Intended Audience :: Developers
Classifier: Intended Audience :: Science/Research
Classifier: License :: OSI Approved :: BSD License
Classifier: Operating System :: OS Independent
Classifier: Programming Language :: Python :: 3.6
Classifier: Programming Language :: Python :: 3.7
Classifier: Programming Language :: Python :: 3.8
Classifier: Programming Language :: Python :: 3.9
Classifier: Programming Language :: Python :: 3.10
Classifier: Programming Language :: Python :: 3.11
Classifier: Topic :: Scientific/Engineering
Classifier: Typing :: Typed
Requires-Python: >=3.6
Requires-Dist: numpy>=1.13.3
Requires-Dist: typing-extensions>=3.7; python_version < '3.8'
Provides-Extra: docs
Requires-Dist: sphinx-book-theme>=0.0.40; extra == 'docs'
Requires-Dist: sphinx-copybutton>=0.3.1; extra == 'docs'
Requires-Dist: sphinx>=4.0; extra == 'docs'
Provides-Extra: test
Requires-Dist: boost-histogram>=1.0; extra == 'test'
Requires-Dist: importlib-metadata>=1.0; python_version < '3.8' and extra == 'test'
Requires-Dist: pytest>=6; extra == 'test'
